seq_align_two_vars/__init__.py
seq_align_two_vars/reference.txt
seq_align_two_vars/seq_align_two_vars.py
seq_align_two_vars/.ipynb_checkpoints/__init__-checkpoint.py
seq_align_two_vars/.ipynb_checkpoints/reference-checkpoint.txt
seq_align_two_vars/.ipynb_checkpoints/seq_align_two_vars-checkpoint.py
seq_align_two_vars/html/seq_align_two_vars.html
seq_align_two_vars/html/.ipynb_checkpoints/seq_align_two_vars-checkpoint.html
seq_align_two_vars-0.1.4.dist-info/METADATA
seq_align_two_vars-0.1.4.dist-info/WHEEL
seq_align_two_vars-0.1.4.dist-info/licenses/LICENSE
seq_align_two_vars-0.1.4.dist-info/RECORD
