Metadata-Version: 2.1
Name: seq_align_two_vars
Version: 0.1.4
Summary: seq_align_two_vars
Project-URL: Homepage, https://gitlab.bucknell.edu/jc092/doc_networks
Project-URL: Bug Tracker, https://gitlab.bucknell.edu/jc092/doc_networks/-/issues
Author-email: Jeffrey Cai <jc092@bucknell.edu>
License-File: LICENSE
Classifier: License :: OSI Approved :: MIT License
Classifier: Operating System :: OS Independent
Classifier: Programming Language :: Python :: 3
Requires-Python: >=3.7
